[
    {
        "image_path": "./asian/american/AME0012.jpg",
        "caption": "A view of a street sign on the side of a road."
    },
    {
        "image_path": "./asian/american/AME003.jpg",
        "caption": "A view of the White House from the balcony of the White House."
    },
    {
        "image_path": "./asian/american/AME009.jpg",
        "caption": "A large statue of the Statue of Liberty on top of a building."
    },
    {
        "image_path": "./asian/american/AME0016.jpg",
        "caption": "A tall tower with a clock on top of it."
    },
    {
        "image_path": "./asian/american/AME002.jpg",
        "caption": "A large dome with a large star in the center of it."
    },
    {
        "image_path": "./asian/american/AME006.jpg",
        "caption": "A view of a bridge over a river."
    }
]